<annotation>
	<folder>images</folder>
	<filename>frameColorW116.jpg</filename>
	<path>D:\trainingWorkingDir\12-2-18\images\frameColorW116.jpg</path>
	<source>
		<database>Unknown</database>
	</source>
	<size>
		<width>640</width>
		<height>480</height>
		<depth>3</depth>
	</size>
	<segmented>0</segmented>
	<object>
		<name>chassis</name>
		<pose>Unspecified</pose>
		<truncated>0</truncated>
		<difficult>0</difficult>
		<bndbox>
			<xmin>105</xmin>
			<ymin>56</ymin>
			<xmax>286</xmax>
			<ymax>211</ymax>
		</bndbox>
	</object>
	<object>
		<name>board</name>
		<pose>Unspecified</pose>
		<truncated>0</truncated>
		<difficult>0</difficult>
		<bndbox>
			<xmin>104</xmin>
			<ymin>97</ymin>
			<xmax>157</xmax>
			<ymax>152</ymax>
		</bndbox>
	</object>
</annotation>
