<annotation>
	<folder>pics</folder>
	<filename>IMG_20180712_100612.jpg</filename>
	<path>C:\Users\Joshua\Desktop\pics\IMG_20180712_100612.jpg</path>
	<source>
		<database>Unknown</database>
	</source>
	<size>
		<width>3024</width>
		<height>4032</height>
		<depth>3</depth>
	</size>
	<segmented>0</segmented>
	<object>
		<name>chassis</name>
		<pose>Unspecified</pose>
		<truncated>0</truncated>
		<difficult>0</difficult>
		<bndbox>
			<xmin>542</xmin>
			<ymin>1024</ymin>
			<xmax>2476</xmax>
			<ymax>3132</ymax>
		</bndbox>
	</object>
	<object>
		<name>qr</name>
		<pose>Unspecified</pose>
		<truncated>0</truncated>
		<difficult>0</difficult>
		<bndbox>
			<xmin>1363</xmin>
			<ymin>1307</ymin>
			<xmax>2072</xmax>
			<ymax>1994</ymax>
		</bndbox>
	</object>
</annotation>
